emoji_generator/__init__.py
emoji_generator/random_emoji.py
emoji_generator-0.7.dist-info/METADATA
emoji_generator-0.7.dist-info/WHEEL
emoji_generator-0.7.dist-info/top_level.txt
emoji_generator-0.7.dist-info/RECORD
