Metadata-Version: 2.1
Name: emoji-generator
Version: 0.7
Summary: A package for working with smiley emojis
Home-page: UNKNOWN
Author: codethreads
Author-email: bellamyy.blakee100@gmail.com
License: UNKNOWN
Platform: UNKNOWN
